pybun-1.3.8.dist-info/METADATA
pybun-1.3.8.dist-info/WHEEL
pybun-1.3.8.dist-info/entry_points.txt
pybun/__init__.py
pybun/__main__.py
pybun/bun
pybun-1.3.8.dist-info/RECORD
