Metadata-Version: 2.3
Name: pybun
Version: 1.3.8
Summary: Bun is an all-in-one toolkit for JavaScript and TypeScript apps.
License: MIT
Classifier: License :: OSI Approved :: MIT License
Project-URL: Homepage, https://bun.sh/
Project-URL: Source Code, https://github.com/oven-sh/bun
Project-URL: Bug Tracker, https://github.com/oven-sh/bun/issues
Project-URL: Changelog, https://bun.sh/blog/bun-v1.3.8
Project-URL: Documentation, https://bun.sh/docs
Requires-Python: ~=3.9
